mmi/__init__.py
mmi/__main__.py
mmi/cli.py
matchmeta-2024.4.14.dist-info/LICENSE
matchmeta-2024.4.14.dist-info/METADATA
matchmeta-2024.4.14.dist-info/WHEEL
matchmeta-2024.4.14.dist-info/entry_points.txt
matchmeta-2024.4.14.dist-info/top_level.txt
matchmeta-2024.4.14.dist-info/RECORD
