Metadata-Version: 2.1
Name: matchmeta
Version: 2024.4.14
Summary: OS Triage for Anyone and Everyone
Home-page: https://github.com/jblukach/mmi
Author: John Lukach
Author-email: hello@lukach.io
License: Apache-2.0
Requires-Python: >=3.7
License-File: LICENSE
Requires-Dist: pybloomfiltermmap3
Requires-Dist: requests
